{
	"$schema": "https://schemas.wp.org/trunk/block.json",
	"apiVersion": 3,
	"name": "roxyapi/get-upagraha-positions",
	"title": "Get upagraha (sub-planet) positions - Upagraha Calculator API (Vedic Astrology)",
	"category": "roxyapi",
	"icon": "database",
	"description": "Get upagraha (sub-planet) positions - Upagraha Calculator API",
	"keywords": [
		"vedic astrology",
		"roxyapi",
		"get",
		"upagraha"
	],
	"version": "1.0.0",
	"textdomain": "roxyapi",
	"supports": {
		"html": false,
		"align": [
			"wide",
			"full"
		],
		"color": {
			"background": true,
			"text": true
		},
		"spacing": {
			"padding": true,
			"margin": true
		}
	},
	"attributes": {
		"date": {
			"type": "string",
			"default": ""
		},
		"time": {
			"type": "string",
			"default": ""
		},
		"latitude": {
			"type": "string",
			"default": ""
		},
		"longitude": {
			"type": "string",
			"default": ""
		},
		"timezone": {
			"type": "string",
			"default": ""
		}
	},
	"render": "file:./render.php"
}
